{
  "main": {
    "id": "c162f0be4898d440",
    "type": "split",
    "children": [
      {
        "id": "80d1a8cbc258f290",
        "type": "tabs",
        "children": [
          {
            "id": "16f5799c345947f8",
            "type": "leaf",
            "state": {
              "type": "markdown",
              "state": {
                "file": "Intro.md",
                "mode": "source",
                "source": false
              }
            }
          }
        ]
      },
      {
        "id": "712c1d1d06283768",
        "type": "tabs",
        "children": [
          {
            "id": "e7119d9acc417b4a",
            "type": "leaf",
            "state": {
              "type": "graph",
              "state": {}
            }
          }
        ]
      }
    ],
    "direction": "vertical"
  },
  "left": {
    "id": "60096340e0dccd1f",
    "type": "split",
    "children": [
      {
        "id": "2055403d22a0dcd8",
        "type": "tabs",
        "children": [
          {
            "id": "7990c00f94227ee5",
            "type": "leaf",
            "state": {
              "type": "file-explorer",
              "state": {
                "sortOrder": "alphabetical"
              }
            }
          },
          {
            "id": "5a50d8c107319991",
            "type": "leaf",
            "state": {
              "type": "search",
              "state": {
                "query": "",
                "matchingCase": false,
                "explainSearch": false,
                "collapseAll": false,
                "extraContext": false,
                "sortOrder": "alphabetical"
              }
            }
          },
          {
            "id": "f889383462db7830",
            "type": "leaf",
            "state": {
              "type": "bookmarks",
              "state": {}
            }
          }
        ]
      }
    ],
    "direction": "horizontal",
    "width": 300
  },
  "right": {
    "id": "5cf15f4cb9c0b13a",
    "type": "split",
    "children": [
      {
        "id": "4507f47e9a2c8e50",
        "type": "tabs",
        "children": [
          {
            "id": "e6d12a26f7e11396",
            "type": "leaf",
            "state": {
              "type": "backlink",
              "state": {
                "file": "Intro.md",
                "collapseAll": false,
                "extraContext": false,
                "sortOrder": "alphabetical",
                "showSearch": false,
                "searchQuery": "",
                "backlinkCollapsed": false,
                "unlinkedCollapsed": true
              }
            }
          },
          {
            "id": "3b8a75bea5582bf8",
            "type": "leaf",
            "state": {
              "type": "outgoing-link",
              "state": {
                "file": "Intro.md",
                "linksCollapsed": false,
                "unlinkedCollapsed": true
              }
            }
          },
          {
            "id": "e1d2a7b9b23afd55",
            "type": "leaf",
            "state": {
              "type": "tag",
              "state": {
                "sortOrder": "frequency",
                "useHierarchy": true
              }
            }
          },
          {
            "id": "827db349a784194b",
            "type": "leaf",
            "state": {
              "type": "outline",
              "state": {
                "file": "Intro.md"
              }
            }
          }
        ]
      }
    ],
    "direction": "horizontal",
    "width": 300,
    "collapsed": true
  },
  "left-ribbon": {
    "hiddenItems": {
      "switcher:Gyors váltó megnyitása": false,
      "graph:Grafikon nézet megnyitása": false,
      "canvas:Új vászon létrehozása": false,
      "daily-notes:Mai jegyzet megnyitása": false,
      "templates:Sablon beszúrása": false,
      "command-palette:Parancspaletta megnyitása": false
    }
  },
  "active": "7990c00f94227ee5",
  "lastOpenFiles": [
    "Intro.md"
  ]
}